muclic/__init__.py
muclic/__main__.py
muclic/album.py
muclic/app.py
muclic/args.py
muclic/logging.py
muclic/media.py
muclic/song.py
muclic/typing.py
muclic-0.9.0.dist-info/LICENSE
muclic-0.9.0.dist-info/METADATA
muclic-0.9.0.dist-info/WHEEL
muclic-0.9.0.dist-info/entry_points.txt
muclic-0.9.0.dist-info/RECORD
