Metadata-Version: 2.1
Name: muclic
Version: 0.9.0
Summary: A cli for downloading music from Youtube Music
License: GPL v3
Author: Cyliann
Author-email: maksymilian@cych.eu
Requires-Python: >=3.12,<4.0
Classifier: License :: Other/Proprietary License
Classifier: Programming Language :: Python :: 3
Classifier: Programming Language :: Python :: 3.12
Classifier: Programming Language :: Python :: 3.13
Requires-Dist: mutagen (>=1.47.0,<2.0.0)
Requires-Dist: requests (>=2.32.3,<3.0.0)
Requires-Dist: yt-dlp (>=2024.11.18,<2025.0.0)
Requires-Dist: ytmusicapi (>=1.8.2,<2.0.0)
